configchecker.py
config_checker-0.0.1.dist-info/LICENSE
config_checker-0.0.1.dist-info/METADATA
config_checker-0.0.1.dist-info/WHEEL
config_checker-0.0.1.dist-info/top_level.txt
config_checker-0.0.1.dist-info/RECORD
