Metadata-Version: 2.1
Name: config-checker
Version: 0.0.1
Summary: Python module wrapper around ConfigParser for enforcing string configuration file operations.
Home-page: https://github.com/stuianna/configChecker
Author: Stuart Ianna
Author-email: stuian@protonmail.com
License: UNKNOWN
Platform: UNKNOWN
Classifier: Programming Language :: Python :: 3
Classifier: License :: OSI Approved :: MIT License
Classifier: Operating System :: OS Independent
Requires-Python: >=3.6
